{
	"format_version": "1.8.0",
	"animations": {
		"animation.ornithomimus.idle": {
			"animation_length": 2,
			"bones": {
				"body3": {
					"rotation": {
						"0.0": [-2.5, 0, 0],
						"1.0": [0, 0, 0],
						"2.0": [-2.5, 0, 0]
					},
					"position": {
						"0.0": [0, 0, 0],
						"1.0": [0, -0.45, 0],
						"2.0": [0, 0, 0]
					}
				},
				"body2": {
					"rotation": {
						"0.0": [-2.5, 0, 0],
						"1.0": [0, 0, 0],
						"2.0": [-2.5, 0, 0]
					}
				},
				"body1": {
					"rotation": {
						"0.0": [0, 0, 0],
						"1.0": [5, 0, 0],
						"2.0": [0, 0, 0]
					}
				},
				"neck1": {
					"rotation": {
						"0.0": [2.5, 0, 0],
						"1.0": [-2.5, 0, 0],
						"2.0": [2.5, 0, 0]
					}
				},
				"neck2": {
					"rotation": {
						"0.0": [2.5, 0, 0],
						"1.0": [0, 0, 0],
						"2.0": [2.5, 0, 0]
					}
				},
				"neck5": {
					"rotation": [0, 0, 0]
				},
				"HeadBase": {
					"rotation": {
						"0.0": [0, 0, 0],
						"1.0": [0, 0, 0],
						"2.0": [0, 0, 0]
					}
				},
				"Throat": {
					"rotation": {
						"0.0": [0, 0, 0],
						"1.0": [2.5, 0, 0],
						"2.0": [0, 0, 0]
					}
				},
				"tail1": {
					"rotation": {
						"0.0": [-5, 2.5, 0],
						"0.5": [-7.5, 0, 0],
						"1.0": [-5, -2.5, 0],
						"1.5": [-7.5, 0, 0],
						"2.0": [-5, 2.5, 0]
					}
				},
				"tail2": {
					"rotation": {
						"0.0": [2.5, 5, -2.5],
						"0.5": [-2.5, 0, 0],
						"1.0": [2.5, -5, 2.5],
						"1.5": [-2.5, 0, 0],
						"2.0": [2.5, 5, -2.5]
					}
				},
				"tail3": {
					"rotation": {
						"0.0": [-2.5, 2.5, -2.5],
						"0.5": [2.5, 0, 0],
						"1.0": [-2.5, -2.5, 2.5],
						"1.5": [2.5, 0, 0],
						"2.0": [-2.5, 2.5, -2.5]
					}
				},
				"tail4": {
					"rotation": {
						"0.0": [-0.5, 5, -5],
						"1.0": [-0.5, -5, 5],
						"2.0": [-0.5, 5, -5]
					}
				}
			}
		},
		"animation.ornithomimus.walk": {
			"loop": true,
			"animation_length": 1,
			"bones": {
				"thigh1": {
					"rotation": {
						"0.0": [-50, 0, 0],
						"0.5": [75, 0, 0],
						"1.0": [-50, 0, 0]
					}
				},
				"foot1": {
					"rotation": {
						"0.25": [-12.5, 0, 0],
						"0.5": [27.5, 0, 0],
						"0.75": [-12.5, 0, 0]
					}
				},
				"thigh2": {
					"rotation": {
						"0.0": [75, 0, 0],
						"0.5": [-50, 0, 0],
						"1.0": [75, 0, 0]
					}
				},
				"foot2": {
					"rotation": {
						"0.0": [27.5, 0, 0],
						"0.25": [-12.5, 0, 0],
						"0.75": [-12.5, 0, 0],
						"1.0": [27.5, 0, 0]
					}
				},
				"body2": {
					"rotation": {
						"0.0": [7.5, 2, 0],
						"0.25": [5, 2, 0],
						"0.5": [7.5, -2, 0],
						"0.75": [5, 2, 0],
						"1.0": [7.5, 2, 0]
					}
				},
				"body1": {
					"rotation": {
						"0.0": [2.5, 5, 0],
						"0.25": [-2.5, 0, 0],
						"0.5": [2.5, "0-5", 0],
						"0.75": [-2.5, 0, 0],
						"1.0": [2.5, 5, 0]
					}
				},
				"HeadBase": {
					"rotation": {
						"0.0": [-2.5, -7.5, 0],
						"0.5": [-2.5, 7.5, 0],
						"1.0": [-2.5, -7.5, 0]
					}
				},
				"Throat": {
					"rotation": [0, 0, 0]
				},
				"tail1": {
					"rotation": {
						"0.0": [2.5, 7.5, 0],
						"0.25": [0, 0, 0],
						"0.5": [2.5, -7.5, 0],
						"0.75": [0, 0, 0],
						"1.0": [2.5, 7.5, 0]
					}
				},
				"tail2": {
					"rotation": {
						"0.0": [5, 5, 0],
						"0.25": [5, 0, 0],
						"0.5": [5, -5, 0],
						"1.0": [5, 5, 0]
					}
				},
				"tail3": {
					"rotation": {
						"0.0": [5, 5, 0],
						"0.25": [-2.5, 0, 0],
						"0.5": [5, -5, 0],
						"0.75": [-2.5, 0, 0],
						"1.0": [5, 5, 0]
					}
				},
				"tail4": {
					"rotation": {
						"0.0": [5, 5, 0],
						"0.25": [-2.5, 0, 0],
						"0.5": [5, -5, 0],
						"0.75": [-2.5, 0, 0],
						"1.0": [5, 5, 0]
					}
				},
				"tail5": {
					"rotation": {
						"0.0": [5, 5, 0],
						"0.25": [0, 0, 0],
						"0.5": [5, -5, 0],
						"0.75": [0, 0, 0],
						"1.0": [5, 5, 0]
					}
				},
				"tail6": {
					"rotation": {
						"0.0": [-5, 8, 0],
						"0.25": [0, 0, 0],
						"0.5": [-5, -8, 0],
						"0.75": [0, 0, 0],
						"1.0": [-5, 8, 0]
					}
				},
				"neck1": {
					"rotation": {
						"0.0": [0, 5, 0],
						"0.5": [0, -5, 0],
						"1.0": [0, 5, 0]
					}
				}
			}
		}
	}
}