{
	"format_version": "1.8.0",
	"animations": {
		"animation.proterosuchus.idle": {
			"animation_length": 2,
			"bones": {
				"bone3": {
					"rotation": {
						"0.0": {
							"vector": [-2.5, 0, 0]
						},
						"1.0": {
							"vector": [2.5, 0, 0],
							"easing": "linear"
						},
						"2.0": {
							"vector": [-2.5, 0, 0]
						}
					}
				},
				"bone4": {
					"rotation": {
						"0.0": {
							"vector": [2.5, 0, 0]
						},
						"1.0": {
							"vector": [-2.5, 0, 0]
						},
						"2.0": {
							"vector": [2.5, 0, 0]
						}
					}
				},
				"bone6": {
					"rotation": {
						"0.0": {
							"vector": [0, 0, 0]
						},
						"0.5": {
							"vector": [2.09, 0, 0]
						},
						"1.0": {
							"vector": [-0.83, 0, 0]
						},
						"1.5": {
							"vector": [2.09, 0, 0]
						},
						"2.0": {
							"vector": [0, 0, 0]
						}
					}
				},
				"bone7": {
					"rotation": {
						"0.0": {
							"vector": [0, 5, 0]
						},
						"1.0": {
							"vector": [-2.5, -5, 0]
						},
						"2.0": {
							"vector": [0, 5, 0]
						}
					}
				},
				"bone8": {
					"rotation": {
						"0.0": {
							"vector": [0, 5, 0]
						},
						"1.0": {
							"vector": [-2.5, -5, 0]
						},
						"2.0": {
							"vector": [0, 5, 0]
						}
					}
				},
				"bone9": {
					"rotation": {
						"0.0": {
							"vector": [0, 5, 0]
						},
						"1.0": {
							"vector": [-2.5, -5, 0]
						},
						"2.0": {
							"vector": [0, 5, 0]
						}
					}
				},
				"bone10": {
					"rotation": {
						"0.0": {
							"vector": [0, 5, 0]
						},
						"1.0": {
							"vector": [-2.5, -5, 0]
						},
						"2.0": {
							"vector": [0, 5, 0]
						}
					}
				}
			}
		}
	},
	"geckolib_format_version": 2
}